MANIFEST.in
README.rst
setup.py
srxraylib/__init__.py
srxraylib/version.py
srxraylib.egg-info/PKG-INFO
srxraylib.egg-info/SOURCES.txt
srxraylib.egg-info/dependency_links.txt
srxraylib.egg-info/not-zip-safe
srxraylib.egg-info/requires.txt
srxraylib.egg-info/top_level.txt
srxraylib/metrology/__init__.py
srxraylib/metrology/dabam.py
srxraylib/metrology/dabam_tests.py
srxraylib/metrology/error_profile_calculator.py
srxraylib/metrology/make_json_summary.py
srxraylib/metrology/profiles_simulation.py
srxraylib/plot/__init__.py
srxraylib/plot/gol.py
srxraylib/profiles/__init__.py
srxraylib/profiles/benders/__init__.py
srxraylib/profiles/benders/bender_io.py
srxraylib/profiles/benders/bender_manager.py
srxraylib/profiles/benders/fixed_rods_bender_manager.py
srxraylib/profiles/benders/flexural_hinge_bender_manager.py
srxraylib/profiles/diaboloid/__init__.py
srxraylib/profiles/diaboloid/diaboloid_calculator.py
srxraylib/profiles/diaboloid/fqs.py
srxraylib/sources/__init__.py
srxraylib/sources/srfunc.py
srxraylib/util/__init__.py
srxraylib/util/chemical_formula.py
srxraylib/util/custom_distribution.py
srxraylib/util/data_structures.py
srxraylib/util/h5_simple_writer.py
srxraylib/util/histograms.py
srxraylib/util/inverse_method_sampler.py
srxraylib/util/random_distributions.py
srxraylib/util/threading.py
srxraylib/waveoptics/CompactAFReader.py
srxraylib/waveoptics/NumpyToSRW.py
srxraylib/waveoptics/__init__.py
srxraylib/waveoptics/polarization.py
srxraylib/waveoptics/propagator.py
srxraylib/waveoptics/propagator2D.py
srxraylib/waveoptics/wavefront.py
srxraylib/waveoptics/wavefront2D.py