Metadata-Version: 2.4
Name: srxraylib
Version: 1.0.64
Summary: Synchrotron Radiation X-ray library
Home-page: https://github.com/oasys-kit/SR-xraylib
Download-URL: https://github.com/oasys-kit/SR-xraylib
Author: Luca Rebuffi, Manuel Sanchez del Rio and Mark Glass
Author-email: lrebuffi@anl.gov
Maintainer: Luca Rebuffi
Maintainer-email: lrebuffi@anl.gov
License: GPLv3
Keywords: x-raysynchrotron radiation,wavefront propagationray tracing,surface metrology,simulation
Classifier: Development Status :: 5 - Production/Stable
Classifier: Environment :: Console
Classifier: Environment :: Plugins
Classifier: Programming Language :: Python :: 3
Classifier: License :: OSI Approved :: GNU General Public License v3 or later (GPLv3+)
Classifier: Operating System :: POSIX
Classifier: Operating System :: Microsoft :: Windows
Classifier: Topic :: Scientific/Engineering :: Visualization
Classifier: Topic :: Software Development :: Libraries :: Python Modules
Classifier: Intended Audience :: Education
Classifier: Intended Audience :: Science/Research
Classifier: Intended Audience :: Developers
Requires-Dist: setuptools
Requires-Dist: numpy
Requires-Dist: scipy
Dynamic: author
Dynamic: author-email
Dynamic: classifier
Dynamic: description
Dynamic: download-url
Dynamic: home-page
Dynamic: keywords
Dynamic: license
Dynamic: maintainer
Dynamic: maintainer-email
Dynamic: requires-dist
Dynamic: summary
